{"is_source_file": true, "format": "TypeScript React (.tsx)", "description": "This file defines a React functional component 'RecipeForm' for creating and editing recipe data within a culinary web application. It manages form state, handles input changes, and renders input fields including ingredients and steps, with options to add and remove elements.", "external_files": ["@/lib/api/types", "@/components/ui"], "external_methods": ["React.useState", "React.useEffect"], "published": ["RecipeForm"], "classes": [], "methods": [{"name": "RecipeForm", "description": "React component for creating/editing recipes with controlled form inputs, managing recipe draft state, and providing UI elements for recipe attributes, ingredients, and preparation steps."}, {"name": "parseTags", "description": "Parses a comma-separated string into an array of trimmed tags."}, {"name": "tagsToString", "description": "Converts an array of tags into a comma-separated string for display."}], "calls": ["setDraft", "React.useState", "map", "filter", "sort", "onChange", "onClick"], "search-terms": ["RecipeForm", "ingredients", "steps", "Draft", "UI components", "React state management"], "state": 2, "file_id": 25, "knowledge_revision": 55, "git_revision": "", "ctags": [], "hash": "23859741604ad8817c74f508a8e4e3e1", "format-version": 4, "code-base-name": "food_recipe_frontend", "filename": "food_recipe_frontend/src/components/RecipeForm.tsx", "revision_history": [{"55": ""}]}